LICENSE.md
README.md
pyproject.toml
configuronic/__init__.py
configuronic/cli.py
configuronic/config.py
configuronic.egg-info/PKG-INFO
configuronic.egg-info/SOURCES.txt
configuronic.egg-info/dependency_links.txt
configuronic.egg-info/requires.txt
configuronic.egg-info/top_level.txt
tests/test_cli.py
tests/test_config.py
tests/test_ipython.py