Metadata-Version: 2.4
Name: configuronic
Version: 0.2.1
Summary: Simple yet powerful "Configuration as Code" library
Author-email: Positronic Robotics <hi@positronic.ro>
License: Copyright (c) 2024-2025 Positronic Robotics Inc.
Project-URL: Homepage, https://github.com/Positronic-Robotics/configuronic
Project-URL: Repository, https://github.com/Positronic-Robotics/configuronic
Project-URL: Issues, https://github.com/Positronic-Robotics/configuronic/issues
Keywords: configuration,config,dependency-injection,yaml
Classifier: Development Status :: 4 - Beta
Classifier: Intended Audience :: Developers
Classifier: License :: OSI Approved :: MIT License
Classifier: Programming Language :: Python :: 3
Classifier: Programming Language :: Python :: 3.10
Classifier: Programming Language :: Python :: 3.11
Classifier: Programming Language :: Python :: 3.12
Classifier: Topic :: Software Development :: Libraries :: Python Modules
Classifier: Topic :: Utilities
Requires-Python: >=3.10
License-File: LICENSE.md
Requires-Dist: PyYAML
Requires-Dist: fire
Provides-Extra: dev
Requires-Dist: pytest; extra == "dev"
Requires-Dist: pytest-cov; extra == "dev"
Requires-Dist: pytest-xdist; extra == "dev"
Requires-Dist: ruff; extra == "dev"
Requires-Dist: numpy; extra == "dev"
Requires-Dist: ipython; extra == "dev"
Dynamic: license-file
